odoo10_addon_shopinvader_product_stock_state-10.0.1.0.0.99.dev5-py3.8-nspkg.pth
odoo/addons/shopinvader_product_stock_state/README.rst
odoo/addons/shopinvader_product_stock_state/__init__.py
odoo/addons/shopinvader_product_stock_state/__manifest__.py
odoo/addons/shopinvader_product_stock_state/i18n/shopinvader_product_stock_state.pot
odoo/addons/shopinvader_product_stock_state/models/__init__.py
odoo/addons/shopinvader_product_stock_state/models/shopinvader_backend.py
odoo/addons/shopinvader_product_stock_state/models/shopinvader_variant.py
odoo/addons/shopinvader_product_stock_state/tests/__init__.py
odoo/addons/shopinvader_product_stock_state/tests/test_product.py
odoo/addons/shopinvader_product_stock_state/views/shopinvader_backend.xml
odoo10_addon_shopinvader_product_stock_state-10.0.1.0.0.99.dev5.dist-info/METADATA
odoo10_addon_shopinvader_product_stock_state-10.0.1.0.0.99.dev5.dist-info/WHEEL
odoo10_addon_shopinvader_product_stock_state-10.0.1.0.0.99.dev5.dist-info/namespace_packages.txt
odoo10_addon_shopinvader_product_stock_state-10.0.1.0.0.99.dev5.dist-info/top_level.txt
odoo10_addon_shopinvader_product_stock_state-10.0.1.0.0.99.dev5.dist-info/RECORD
